Metadata-Version: 1.0
Name: dsnd-probability-GS
Version: 1.2
Summary: Gaussian and Binomail distributions
Home-page: UNKNOWN
Author: Gurnek
Author-email: UNKNOWN
License: UNKNOWN
Platform: UNKNOWN
